<StringGroup>
  <String>
    <Code>OPERATION_TITLE</Code>
    <PositionFlag>272</PositionFlag>
    <CharSpace>1</CharSpace>
    <LineSpace>1</LineSpace>
    <TabSpace>1</TabSpace>
    <Color>-1</Color>
    <Size>1</Size>
    <ID>OPERATION_TITLE</ID>
  </String>
  <String>
    <Code>OPERATION_MISSION</Code>
    <PositionFlag>272</PositionFlag>
    <CharSpace>1</CharSpace>
    <LineSpace>1</LineSpace>
    <TabSpace>1</TabSpace>
    <Color>-16777216</Color>
    <Size>0.8</Size>
    <ID>OPERATION_MISSION</ID>
  </String>
  <String>
    <Code>OPERATION_BUTTON_INFO_01</Code>
    <PositionFlag>272</PositionFlag>
    <CharSpace>1</CharSpace>
    <LineSpace>1</LineSpace>
    <TabSpace>1</TabSpace>
    <Color>-1</Color>
    <Size>0.9</Size>
    <ID>OPERATION_BUTTON_INFO_01</ID>
  </String>
  <String>
    <Code>OPERATION_WIN</Code>
    <PositionFlag>256</PositionFlag>
    <CharSpace>1</CharSpace>
    <LineSpace>1</LineSpace>
    <TabSpace>1</TabSpace>
    <Color>-7275777</Color>
    <Size>1.2</Size>
    <ID>OPERATION_WIN</ID>
  </String>
  <String>
    <Code>OPERATION_WIN_CONTENT</Code>
    <PositionFlag>256</PositionFlag>
    <CharSpace>1</CharSpace>
    <LineSpace>1</LineSpace>
    <TabSpace>1</TabSpace>
    <Color>-1</Color>
    <Size>1</Size>
    <ID>OPERATION_WIN_CONTENT</ID>
  </String>
  <String>
    <Code>OPERATION_LOSS</Code>
    <PositionFlag>256</PositionFlag>
    <CharSpace>1</CharSpace>
    <LineSpace>1</LineSpace>
    <TabSpace>1</TabSpace>
    <Color>-7275777</Color>
    <Size>1.2</Size>
    <ID>OPERATION_LOSS</ID>
  </String>
  <String>
    <Code>OPERATION_LOSS_CONTENT</Code>
    <PositionFlag>256</PositionFlag>
    <CharSpace>1</CharSpace>
    <LineSpace>1</LineSpace>
    <TabSpace>1</TabSpace>
    <Color>-1</Color>
    <Size>1</Size>
    <ID>OPERATION_LOSS_CONTENT</ID>
  </String>
  <String>
    <Code>OPERATION_COMMENT</Code>
    <PositionFlag>256</PositionFlag>
    <CharSpace>1</CharSpace>
    <LineSpace>1</LineSpace>
    <TabSpace>1</TabSpace>
    <Color>-7275777</Color>
    <Size>1.2</Size>
    <ID>OPERATION_COMMENT</ID>
  </String>
  <String>
    <Code>OPERATION_COMMENT_CONTENT</Code>
    <PositionFlag>256</PositionFlag>
    <CharSpace>1</CharSpace>
    <LineSpace>1</LineSpace>
    <TabSpace>5</TabSpace>
    <Color>-1</Color>
    <Size>1</Size>
    <ID>OPERATION_COMMENT_CONTENT</ID>
  </String>
</StringGroup>