[
  {
    "ID": "CHAT_A_BTN_01",
    "Text": null,
    "Lines": [
      "∈"
    ],
    "TabSpace": null,
    "Size": null
  },
  {
    "ID": "eve266",
    "Text": null,
    "Lines": [
      "近日実施予定の、アフリカ大陸への大規模掃討作戦に向けて、",
      "参加部隊がオデッサに集結中だ。　しかし、その背面にあたる",
      "地区に、ジオンの敗走部隊が潜伏しているとの情報が入った。"
    ],
    "TabSpace": null,
    "Size": null
  },
  {
    "ID": "eve267",
    "Text": null,
    "Lines": [
      "私たちに、その敵を捜索、殲滅しろってわけね。"
    ],
    "TabSpace": null,
    "Size": null
  },
  {
    "ID": "eve268",
    "Text": null,
    "Lines": [
      "この状況下で、部隊としての機能を維持しているってことは、",
      "敵の部隊指揮官は、相当のてだれだな…。"
    ],
    "TabSpace": null,
    "Size": null
  },
  {
    "ID": "eve269",
    "Text": null,
    "Lines": [
      "補給もままならず、絶望的ともいえる状況下で、死を覚悟",
      "するような戦闘を強いるわけですからね…。"
    ],
    "TabSpace": null,
    "Size": null
  },
  {
    "ID": "eve270",
    "Text": null,
    "Lines": [
      "そうだ。",
      "今回の敵は、かなり手ごわいと思っていいだろう。"
    ],
    "TabSpace": null,
    "Size": null
  },
  {
    "ID": "eve271",
    "Text": null,
    "Lines": [
      "気を引き締めていかないと、こっちがやられる…か。"
    ],
    "TabSpace": null,
    "Size": null
  },
  {
    "ID": "eve272",
    "Text": null,
    "Lines": [
      "本部じゃ、地上の掃討作戦は、もう消化試合程度に",
      "考えてるからな。",
      "最後の詰めにこそ、戦力を余剰投入するべきなのによ。"
    ],
    "TabSpace": null,
    "Size": null
  },
  {
    "ID": "eve273",
    "Text": null,
    "Lines": [
      "大きな反撃もできない地上の残党を後回しにして、宇宙に戦力を",
      "集中…、一気に終戦させたいっていう、レビル将軍の思惑は",
      "分かるけどね。"
    ],
    "TabSpace": null,
    "Size": null
  },
  {
    "ID": "eve274",
    "Text": null,
    "Lines": [
      "ジャブローに残って、地上部隊を指揮してる方々には、",
      "利己主義の狸さんが多いですから。"
    ],
    "TabSpace": null,
    "Size": null
  },
  {
    "ID": "eve275",
    "Text": null,
    "Lines": [
      "ハハハ…。　せいぜい化かされて、命まで落とすことにならないよう",
      "気をつけるさ。　この戦争はもうすぐ終る…。",
      "全員生き残ろう！　ユニット1、出撃だ！"
    ],
    "TabSpace": null,
    "Size": null
  },
  {
    "ID": "eve702",
    "Text": null,
    "Lines": [
      "了解！"
    ],
    "TabSpace": null,
    "Size": null
  }
]