[
  {
    "FileName": "sound/stream/ber001.brstm",
    "Translation": "I'm a soldier.",
    "Miliseconds": 5000,
    "Color": "Yellow",
    "Enabled": true,
    "AllowDuplicate": false,
    "Scale": 2.0
  },
  {
    "FileName": "sound/stream/ber148.brstm",
    "Translation": "ber148.brstm",
    "Miliseconds": 5000,
    "Color": "Yellow",
    "Enabled": true,
    "AllowDuplicate": false,
    "Scale": 2.0
  },
  {
    "FileName": "sound/stream/eva126.brstm",
    "Translation": "eva126.brstm",
    "Miliseconds": 5000,
    "Color": "Yellow",
    "Enabled": true,
    "AllowDuplicate": false,
    "Scale": 2.0
  },
  {
    "FileName": "sound/stream/ber002.brstm",
    "Translation": "I can't run away",
    "Miliseconds": 5000,
    "Color": "Yellow",
    "Enabled": true,
    "AllowDuplicate": false,
    "Scale": 2.0
  },
  {
    "FileName": "sound/stream/crs003.brstm",
    "Translation": "crs003.brstm",
    "Miliseconds": 5000,
    "Color": "Yellow",
    "Enabled": true,
    "AllowDuplicate": false,
    "Scale": 2.0
  },
  {
    "FileName": "sound/stream/eva125.brstm",
    "Translation": "eva125.brstm",
    "Miliseconds": 5000,
    "Color": "Yellow",
    "Enabled": true,
    "AllowDuplicate": false,
    "Scale": 2.0
  }
]