[
  {
    "ID": "OPERATION_WIN_CONTENT",
    "Text": null,
    "Lines": [
      "Locate and defend Medea Transport",
      "Search and Destroy"
    ],
    "TabSpace": null,
    "Size": null
  },
  {
    "ID": "OPERATION_LOSS_CONTENT",
    "Text": null,
    "Lines": [
      "Destruction of your MS.",
      "Destruction of Medea Transport"
    ],
    "TabSpace": null,
    "Size": null
  },
  {
    "ID": "OPERATION_COMMENT_CONTENT",
    "Text": null,
    "Lines": [
      "Secure Medea before enemy forces",
      "can reach it."
    ],
    "TabSpace": null,
    "Size": null
  },
  {
    "ID": "BR_DATA_A_01",
    "Text": null,
    "Lines": [
      "LOST"
    ],
    "TabSpace": null,
    "Size": null
  },
  {
    "ID": "BR_DATA_A_02",
    "Text": null,
    "Lines": [
      "Medea Transport"
    ],
    "TabSpace": null,
    "Size": null
  },
  {
    "ID": "BR_DATA_B_01",
    "Text": null,
    "Lines": [
      "FIELD"
    ],
    "TabSpace": null,
    "Size": null
  },
  {
    "ID": "BR_DATA_B_02",
    "Text": null,
    "Lines": [
      "Area 526"
    ],
    "TabSpace": null,
    "Size": null
  },
  {
    "ID": "BR_DATA_C_01",
    "Text": null,
    "Lines": [
      "ZEON"
    ],
    "TabSpace": null,
    "Size": null
  },
  {
    "ID": "BR_DATA_C_02",
    "Text": null,
    "Lines": [
      "Enemy troops",
      "apporaching"
    ],
    "TabSpace": null,
    "Size": null
  },
  {
    "ID": "BR_DATA_D_01",
    "Text": null,
    "Lines": [
      "DEFENSE"
    ],
    "TabSpace": null,
    "Size": null
  },
  {
    "ID": "BR_DATA_D_02",
    "Text": null,
    "Lines": [
      "Medea Transport"
    ],
    "TabSpace": null,
    "Size": null
  },
  {
    "ID": "BR_INFO_A_01",
    "Text": null,
    "Lines": [
      "This is an urgent mission."
    ],
    "TabSpace": null,
    "Size": null
  },
  {
    "ID": "BR_INFO_A_02",
    "Text": null,
    "Lines": [
      "Medea Transport carrying supplies went missing",
      "in valley of Area 526."
    ],
    "TabSpace": null,
    "Size": null
  },
  {
    "ID": "BR_INFO_B_01",
    "Text": null,
    "Lines": [
      "This valley was used as bombing range by",
      "Zeon Far Easy army."
    ],
    "TabSpace": null,
    "Size": null
  },
  {
    "ID": "BR_INFO_C_01",
    "Text": null,
    "Lines": [
      "Medea attempted to pass use siege of Lhasa",
      "as a distraction to passthrough safely."
    ],
    "TabSpace": null,
    "Size": null
  },
  {
    "ID": "BR_INFO_C_02",
    "Text": null,
    "Lines": [
      "We don't know if dissapearance is caused",
      "by enemy, but cargo must be secured."
    ],
    "TabSpace": null,
    "Size": null
  },
  {
    "ID": "BR_INFO_D_01",
    "Text": null,
    "Lines": [
      "Assuming worst, SRT-1 is to search the valluy",
      "for Medea Transport."
    ],
    "TabSpace": null,
    "Size": null
  },
  {
    "ID": "BR_INFO_D_02",
    "Text": null,
    "Lines": [
      "Prioritize defense of Medea while",
      "dealing with enemy forces."
    ],
    "TabSpace": null,
    "Size": null
  },
  {
    "ID": "BR_INFO_D_03",
    "Text": null,
    "Lines": [
      "Well then, I wish you good luck!"
    ],
    "TabSpace": null,
    "Size": null
  }
]